setup.py
ipythontools/__init__.py
ipythontools/ipynb2article.py
ipythontools/spellchecker.py
ipythontools.egg-info/PKG-INFO
ipythontools.egg-info/SOURCES.txt
ipythontools.egg-info/dependency_links.txt
ipythontools.egg-info/entry_points.txt
ipythontools.egg-info/top_level.txt