Metadata-Version: 1.1
Name: ipythontools
Version: 0.1.0
Summary: Jupyter/IPython notebook to latex converter and spell checker
Home-page: https://github.com/hamogu/ipythontools
Author: Hans Moritz Gunther
Author-email: moritz.guenther@gmx.de
License: MIT
Keywords: ipython latex notebok jupyter
Platform: UNKNOWN
Classifier: Development Status :: 3 - Alpha
Classifier: Environment :: Console
Classifier: Intended Audience :: Science/Research
Classifier: License :: OSI Approved :: MIT License
Classifier: Topic :: Text Processing :: Markup :: LaTeX
Classifier: Topic :: Utilities
Requires: pyenchant
